{
  "id": "036LxbpsZt0VzZAgxYOEM5",
  "name": "Spencer Barnett",
  "uri": "spotify:artist:036LxbpsZt0VzZAgxYOEM5",
  "followers": {
    "href": null,
    "total": 12150
  },
  "genres": [
    "modern indie pop"
  ],
  "images": [
    {
      "height": 640,
      "url": "https://i.scdn.co/image/ab6761610000e5eb74a597878d689973b8bf0f76",
      "width": 640
    },
    {
      "height": 320,
      "url": "https://i.scdn.co/image/ab6761610000517474a597878d689973b8bf0f76",
      "width": 320
    },
    {
      "height": 160,
      "url": "https://i.scdn.co/image/ab6761610000f17874a597878d689973b8bf0f76",
      "width": 160
    }
  ],
  "popularity": 12,
  "external_urls": {
    "spotify": "https://open.spotify.com/artist/036LxbpsZt0VzZAgxYOEM5"
  }
}