{"id":"03FGY5MFUz7JNP6yYbiceB","name":"Quimi Portet","uri":"spotify:artist:03FGY5MFUz7JNP6yYbiceB","followers":{"href":null,"total":14043},"genres":["cantautor catala","indie catala","rock catala"],"images":[{"url":"https://i.scdn.co/image/ab6761610000e5eb39eff23c41edb100caa8e6c2","height":640,"width":640},{"url":"https://i.scdn.co/image/ab6761610000517439eff23c41edb100caa8e6c2","height":320,"width":320},{"url":"https://i.scdn.co/image/ab6761610000f17839eff23c41edb100caa8e6c2","height":160,"width":160}],"popularity":28,"external_urls":{"spotify":"https://open.spotify.com/artist/03FGY5MFUz7JNP6yYbiceB"}}