{"id":"06SP1uJIHeFuNvkKJ3tRc6","name":"Sally Dige","uri":"spotify:artist:06SP1uJIHeFuNvkKJ3tRc6","followers":{"href":null,"total":14968},"genres":["canadian post-punk","dark post-punk","grave wave","minimal wave","multidisciplinary"],"images":[{"url":"https://i.scdn.co/image/ab6761610000e5ebe8927ecb67bffdbc2afedb17","height":640,"width":640},{"url":"https://i.scdn.co/image/ab67616100005174e8927ecb67bffdbc2afedb17","height":320,"width":320},{"url":"https://i.scdn.co/image/ab6761610000f178e8927ecb67bffdbc2afedb17","height":160,"width":160}],"popularity":22,"external_urls":{"spotify":"https://open.spotify.com/artist/06SP1uJIHeFuNvkKJ3tRc6"}}