{
  "id": "08vFQnEXaS9I7VZ2TIXBf3",
  "name": "Derniere Volonte",
  "uri": "spotify:artist:08vFQnEXaS9I7VZ2TIXBf3",
  "followers": {
    "href": null,
    "total": 9571
  },
  "genres": [
    "martial industrial",
    "neofolk"
  ],
  "images": [
    {
      "height": 640,
      "url": "https://i.scdn.co/image/ab67616d0000b273ab233f06319c09b958012890",
      "width": 640
    },
    {
      "height": 300,
      "url": "https://i.scdn.co/image/ab67616d00001e02ab233f06319c09b958012890",
      "width": 300
    },
    {
      "height": 64,
      "url": "https://i.scdn.co/image/ab67616d00004851ab233f06319c09b958012890",
      "width": 64
    }
  ],
  "popularity": 18,
  "external_urls": {
    "spotify": "https://open.spotify.com/artist/08vFQnEXaS9I7VZ2TIXBf3"
  }
}