{
  "id": "08wI0NdxcVZnDFVykhbE2D",
  "name": "Sucker Punch",
  "uri": "spotify:artist:08wI0NdxcVZnDFVykhbE2D",
  "followers": {
    "href": null,
    "total": 1474
  },
  "genres": [

  ],
  "images": [
    {
      "height": 640,
      "url": "https://i.scdn.co/image/ab6761610000e5eb085ac8fc50e651edcec1dfdf",
      "width": 640
    },
    {
      "height": 320,
      "url": "https://i.scdn.co/image/ab67616100005174085ac8fc50e651edcec1dfdf",
      "width": 320
    },
    {
      "height": 160,
      "url": "https://i.scdn.co/image/ab6761610000f178085ac8fc50e651edcec1dfdf",
      "width": 160
    }
  ],
  "popularity": 9,
  "external_urls": {
    "spotify": "https://open.spotify.com/artist/08wI0NdxcVZnDFVykhbE2D"
  }
}