{"id":"0cN2xWiVgSFG5yIArYq0PM","name":"Los Trovadores De La Lírica Perdida","uri":"spotify:artist:0cN2xWiVgSFG5yIArYq0PM","followers":{"href":null,"total":1395},"genres":["spanish hip hop"],"images":[{"url":"https://i.scdn.co/image/ab6761610000e5ebe5e30e78f8e03e5adc575bab","height":640,"width":640},{"url":"https://i.scdn.co/image/ab67616100005174e5e30e78f8e03e5adc575bab","height":320,"width":320},{"url":"https://i.scdn.co/image/ab6761610000f178e5e30e78f8e03e5adc575bab","height":160,"width":160}],"popularity":14,"external_urls":{"spotify":"https://open.spotify.com/artist/0cN2xWiVgSFG5yIArYq0PM"}}