{
  "id": "0E62pGEp8pWSbgmv2k54PK",
  "name": "Alexa Ro",
  "uri": "spotify:artist:0E62pGEp8pWSbgmv2k54PK",
  "followers": {
    "href": null,
    "total": 189
  },
  "genres": [

  ],
  "images": [
    {
      "height": 640,
      "url": "https://i.scdn.co/image/ab6761610000e5ebaef868a06543e2396d40ee90",
      "width": 640
    },
    {
      "height": 320,
      "url": "https://i.scdn.co/image/ab67616100005174aef868a06543e2396d40ee90",
      "width": 320
    },
    {
      "height": 160,
      "url": "https://i.scdn.co/image/ab6761610000f178aef868a06543e2396d40ee90",
      "width": 160
    }
  ],
  "popularity": 5,
  "external_urls": {
    "spotify": "https://open.spotify.com/artist/0E62pGEp8pWSbgmv2k54PK"
  }
}