{
  "id": "0nv3BRJ9Rq6Ke2VXH7sINv",
  "name": "Piss Lizard",
  "uri": "spotify:artist:0nv3BRJ9Rq6Ke2VXH7sINv",
  "followers": {
    "href": null,
    "total": 100
  },
  "genres": [

  ],
  "images": [
    {
      "height": 640,
      "url": "https://i.scdn.co/image/ab6761610000e5eb660580c362be7833c2163f85",
      "width": 640
    },
    {
      "height": 320,
      "url": "https://i.scdn.co/image/ab67616100005174660580c362be7833c2163f85",
      "width": 320
    },
    {
      "height": 160,
      "url": "https://i.scdn.co/image/ab6761610000f178660580c362be7833c2163f85",
      "width": 160
    }
  ],
  "popularity": 0,
  "external_urls": {
    "spotify": "https://open.spotify.com/artist/0nv3BRJ9Rq6Ke2VXH7sINv"
  }
}