{
  "id": "0oGnYXdjbDTggEWk0ckmQU",
  "name": "Andy Hart",
  "uri": "spotify:artist:0oGnYXdjbDTggEWk0ckmQU",
  "followers": {
    "href": null,
    "total": 7088
  },
  "genres": [
    "deep soul house",
    "float house"
  ],
  "images": [
    {
      "height": 640,
      "url": "https://i.scdn.co/image/ab67616d0000b2736f77b5ba6839d48e46c21cf9",
      "width": 640
    },
    {
      "height": 300,
      "url": "https://i.scdn.co/image/ab67616d00001e026f77b5ba6839d48e46c21cf9",
      "width": 300
    },
    {
      "height": 64,
      "url": "https://i.scdn.co/image/ab67616d000048516f77b5ba6839d48e46c21cf9",
      "width": 64
    }
  ],
  "popularity": 23,
  "external_urls": {
    "spotify": "https://open.spotify.com/artist/0oGnYXdjbDTggEWk0ckmQU"
  }
}