{"id":"0PajLDK4vA1VnOVyYYO7Ae","name":"Mucho Muchacho","uri":"spotify:artist:0PajLDK4vA1VnOVyYYO7Ae","followers":{"href":null,"total":24873},"genres":["rap underground espanol","spanish hip hop"],"images":[{"url":"https://i.scdn.co/image/ab6761610000e5ebfe3c7265a171930c21f6b3db","height":640,"width":640},{"url":"https://i.scdn.co/image/ab67616100005174fe3c7265a171930c21f6b3db","height":320,"width":320},{"url":"https://i.scdn.co/image/ab6761610000f178fe3c7265a171930c21f6b3db","height":160,"width":160}],"popularity":39,"external_urls":{"spotify":"https://open.spotify.com/artist/0PajLDK4vA1VnOVyYYO7Ae"}}