{"id":"0TMLPi3f3qrkHV8y7Ccvec","name":"Shravan Sridhar","uri":"spotify:artist:0TMLPi3f3qrkHV8y7Ccvec","followers":{"href":null,"total":3510},"genres":["indian indie","hindi indie","tamil indie"],"images":[{"url":"https://i.scdn.co/image/ab6761610000e5eb8117311aa5c43be91c8d225f","height":640,"width":640},{"url":"https://i.scdn.co/image/ab676161000051748117311aa5c43be91c8d225f","height":320,"width":320},{"url":"https://i.scdn.co/image/ab6761610000f1788117311aa5c43be91c8d225f","height":160,"width":160}],"popularity":39,"external_urls":{"spotify":"https://open.spotify.com/artist/0TMLPi3f3qrkHV8y7Ccvec"}}