{"id":"14itayizvSheiiSLn0MhER","name":"Lillo Thomas","uri":"spotify:artist:14itayizvSheiiSLn0MhER","followers":{"href":null,"total":13952},"genres":["new jack swing","post-disco","post-disco soul"],"images":[{"url":"https://i.scdn.co/image/ab6761610000e5eb15de72e8141e7b9de9dc2113","height":640,"width":640},{"url":"https://i.scdn.co/image/ab6761610000517415de72e8141e7b9de9dc2113","height":320,"width":320},{"url":"https://i.scdn.co/image/ab6761610000f17815de72e8141e7b9de9dc2113","height":160,"width":160}],"popularity":33,"external_urls":{"spotify":"https://open.spotify.com/artist/14itayizvSheiiSLn0MhER"}}