{
  "id": "15xXcGzGTDiBrXsfMlSxca",
  "name": "GOOD MORNING SUNSHINE",
  "uri": "spotify:artist:15xXcGzGTDiBrXsfMlSxca",
  "followers": {
    "href": null,
    "total": 108
  },
  "genres": [

  ],
  "images": [
    {
      "height": 640,
      "url": "https://i.scdn.co/image/ab67616d0000b2732aa17b9649c3f58f91c92997",
      "width": 640
    },
    {
      "height": 300,
      "url": "https://i.scdn.co/image/ab67616d00001e022aa17b9649c3f58f91c92997",
      "width": 300
    },
    {
      "height": 64,
      "url": "https://i.scdn.co/image/ab67616d000048512aa17b9649c3f58f91c92997",
      "width": 64
    }
  ],
  "popularity": 0,
  "external_urls": {
    "spotify": "https://open.spotify.com/artist/15xXcGzGTDiBrXsfMlSxca"
  }
}