{
  "id": "18EAcDza5wHvJw5MVSsIS9",
  "name": "Terran Severance",
  "uri": "spotify:artist:18EAcDza5wHvJw5MVSsIS9",
  "followers": {
    "href": null,
    "total": 126
  },
  "genres": [

  ],
  "images": [
    {
      "height": 640,
      "url": "https://i.scdn.co/image/ab6761610000e5ebc2fdb10ac40210219c903ca2",
      "width": 640
    },
    {
      "height": 320,
      "url": "https://i.scdn.co/image/ab67616100005174c2fdb10ac40210219c903ca2",
      "width": 320
    },
    {
      "height": 160,
      "url": "https://i.scdn.co/image/ab6761610000f178c2fdb10ac40210219c903ca2",
      "width": 160
    }
  ],
  "popularity": 0,
  "external_urls": {
    "spotify": "https://open.spotify.com/artist/18EAcDza5wHvJw5MVSsIS9"
  }
}