{
  "id": "1gA55xnafhPiBIM07ZlXHA",
  "name": "Hexis",
  "uri": "spotify:artist:1gA55xnafhPiBIM07ZlXHA",
  "followers": {
    "href": null,
    "total": 15987
  },
  "genres": [
    "blackened crust",
    "blackgaze",
    "danish black metal",
    "drone metal",
    "post-black metal",
    "post-metal",
    "sludgecore"
  ],
  "images": [
    {
      "height": 640,
      "url": "https://i.scdn.co/image/ab6761610000e5eb845d4daaf0a3efd5ecaba3e2",
      "width": 640
    },
    {
      "height": 320,
      "url": "https://i.scdn.co/image/ab67616100005174845d4daaf0a3efd5ecaba3e2",
      "width": 320
    },
    {
      "height": 160,
      "url": "https://i.scdn.co/image/ab6761610000f178845d4daaf0a3efd5ecaba3e2",
      "width": 160
    }
  ],
  "popularity": 26,
  "external_urls": {
    "spotify": "https://open.spotify.com/artist/1gA55xnafhPiBIM07ZlXHA"
  }
}