{
  "id": "1go10OxHP4fyGsyWfJcFEh",
  "name": "Malik Elijah",
  "uri": "spotify:artist:1go10OxHP4fyGsyWfJcFEh",
  "followers": {
    "href": null,
    "total": 10887
  },
  "genres": [

  ],
  "images": [
    {
      "height": 640,
      "url": "https://i.scdn.co/image/ab6761610000e5eb26b66860f766290dc0987a9f",
      "width": 640
    },
    {
      "height": 320,
      "url": "https://i.scdn.co/image/ab6761610000517426b66860f766290dc0987a9f",
      "width": 320
    },
    {
      "height": 160,
      "url": "https://i.scdn.co/image/ab6761610000f17826b66860f766290dc0987a9f",
      "width": 160
    }
  ],
  "popularity": 31,
  "external_urls": {
    "spotify": "https://open.spotify.com/artist/1go10OxHP4fyGsyWfJcFEh"
  }
}