{
  "id": "1HWIqepzFhm117OWygDEWQ",
  "name": "PLEVAIL",
  "uri": "spotify:artist:1HWIqepzFhm117OWygDEWQ",
  "followers": {
    "href": null,
    "total": 1076
  },
  "genres": [
    "alt-idol"
  ],
  "images": [
    {
      "height": 640,
      "url": "https://i.scdn.co/image/ab6761610000e5ebcb4a5fcad6dd20db1a7e2ac8",
      "width": 640
    },
    {
      "height": 320,
      "url": "https://i.scdn.co/image/ab67616100005174cb4a5fcad6dd20db1a7e2ac8",
      "width": 320
    },
    {
      "height": 160,
      "url": "https://i.scdn.co/image/ab6761610000f178cb4a5fcad6dd20db1a7e2ac8",
      "width": 160
    }
  ],
  "popularity": 13,
  "external_urls": {
    "spotify": "https://open.spotify.com/artist/1HWIqepzFhm117OWygDEWQ"
  }
}