{"id":"1nQj0M42wlxHPw999Pms69","name":"Swimming Tapes","uri":"spotify:artist:1nQj0M42wlxHPw999Pms69","followers":{"href":null,"total":31508},"genres":["chill dream pop","english indie rock"],"images":[{"url":"https://i.scdn.co/image/ab6761610000e5ebc0f6c43b319307dea0ace8cf","height":640,"width":640},{"url":"https://i.scdn.co/image/ab67616100005174c0f6c43b319307dea0ace8cf","height":320,"width":320},{"url":"https://i.scdn.co/image/ab6761610000f178c0f6c43b319307dea0ace8cf","height":160,"width":160}],"popularity":31,"external_urls":{"spotify":"https://open.spotify.com/artist/1nQj0M42wlxHPw999Pms69"}}