{"id":"1pB7DnYxsE4QaV9rI6VMwc","name":"Tano Romano","uri":"spotify:artist:1pB7DnYxsE4QaV9rI6VMwc","followers":{"href":null,"total":14269},"genres":["argentine heavy metal","argentine metal"],"images":[{"url":"https://i.scdn.co/image/ab6761610000e5eb20398a347ff973b1e7acca06","height":640,"width":640},{"url":"https://i.scdn.co/image/ab6761610000517420398a347ff973b1e7acca06","height":320,"width":320},{"url":"https://i.scdn.co/image/ab6761610000f17820398a347ff973b1e7acca06","height":160,"width":160}],"popularity":16,"external_urls":{"spotify":"https://open.spotify.com/artist/1pB7DnYxsE4QaV9rI6VMwc"}}