{
  "id": "1qBYZysddNFQXTLFieIIJx",
  "name": "HECHIZERO",
  "uri": "spotify:artist:1qBYZysddNFQXTLFieIIJx",
  "followers": {
    "href": null,
    "total": 26
  },
  "genres": [

  ],
  "images": [
    {
      "height": 640,
      "url": "https://i.scdn.co/image/ab6761610000e5ebde8c8eb3fda2ef232cc9ea3c",
      "width": 640
    },
    {
      "height": 320,
      "url": "https://i.scdn.co/image/ab67616100005174de8c8eb3fda2ef232cc9ea3c",
      "width": 320
    },
    {
      "height": 160,
      "url": "https://i.scdn.co/image/ab6761610000f178de8c8eb3fda2ef232cc9ea3c",
      "width": 160
    }
  ],
  "popularity": 0,
  "external_urls": {
    "spotify": "https://open.spotify.com/artist/1qBYZysddNFQXTLFieIIJx"
  }
}