{
  "id": "1SuCg7zQMOg0BbzDYjIByT",
  "name": "Soft Cricket",
  "uri": "spotify:artist:1SuCg7zQMOg0BbzDYjIByT",
  "followers": {
    "href": null,
    "total": 145
  },
  "genres": [

  ],
  "images": [
    {
      "height": 640,
      "url": "https://i.scdn.co/image/ab6761610000e5ebc9f39e984b00ca8b0be5a1ba",
      "width": 640
    },
    {
      "height": 320,
      "url": "https://i.scdn.co/image/ab67616100005174c9f39e984b00ca8b0be5a1ba",
      "width": 320
    },
    {
      "height": 160,
      "url": "https://i.scdn.co/image/ab6761610000f178c9f39e984b00ca8b0be5a1ba",
      "width": 160
    }
  ],
  "popularity": 0,
  "external_urls": {
    "spotify": "https://open.spotify.com/artist/1SuCg7zQMOg0BbzDYjIByT"
  }
}