{
  "id": "1T7A3AeYN1sxi951hJUJVK",
  "name": "RITCHRD",
  "uri": "spotify:artist:1T7A3AeYN1sxi951hJUJVK",
  "followers": {
    "href": null,
    "total": 6673
  },
  "genres": [
    "future funk"
  ],
  "images": [
    {
      "height": 640,
      "url": "https://i.scdn.co/image/ab6761610000e5ebe6ac214519d745b64a5fb409",
      "width": 640
    },
    {
      "height": 320,
      "url": "https://i.scdn.co/image/ab67616100005174e6ac214519d745b64a5fb409",
      "width": 320
    },
    {
      "height": 160,
      "url": "https://i.scdn.co/image/ab6761610000f178e6ac214519d745b64a5fb409",
      "width": 160
    }
  ],
  "popularity": 30,
  "external_urls": {
    "spotify": "https://open.spotify.com/artist/1T7A3AeYN1sxi951hJUJVK"
  }
}