{
  "id": "2A61sQntb4CUdnHQeb2tog",
  "name": "Juno Francis",
  "uri": "spotify:artist:2A61sQntb4CUdnHQeb2tog",
  "followers": {
    "href": null,
    "total": 3764
  },
  "genres": [

  ],
  "images": [
    {
      "height": 640,
      "url": "https://i.scdn.co/image/ab6761610000e5ebea725a2759374130c5a6bbeb",
      "width": 640
    },
    {
      "height": 320,
      "url": "https://i.scdn.co/image/ab67616100005174ea725a2759374130c5a6bbeb",
      "width": 320
    },
    {
      "height": 160,
      "url": "https://i.scdn.co/image/ab6761610000f178ea725a2759374130c5a6bbeb",
      "width": 160
    }
  ],
  "popularity": 18,
  "external_urls": {
    "spotify": "https://open.spotify.com/artist/2A61sQntb4CUdnHQeb2tog"
  }
}