{
  "id": "2G0P9pMMbNRVMwaeOEIbb7",
  "name": "Cainan Francis",
  "uri": "spotify:artist:2G0P9pMMbNRVMwaeOEIbb7",
  "followers": {
    "href": null,
    "total": 207
  },
  "genres": [

  ],
  "images": [
    {
      "height": 640,
      "url": "https://i.scdn.co/image/ab6761610000e5ebdc19af27a57dd42e98de5b48",
      "width": 640
    },
    {
      "height": 320,
      "url": "https://i.scdn.co/image/ab67616100005174dc19af27a57dd42e98de5b48",
      "width": 320
    },
    {
      "height": 160,
      "url": "https://i.scdn.co/image/ab6761610000f178dc19af27a57dd42e98de5b48",
      "width": 160
    }
  ],
  "popularity": 0,
  "external_urls": {
    "spotify": "https://open.spotify.com/artist/2G0P9pMMbNRVMwaeOEIbb7"
  }
}