{
  "id": "2gfEBGQv2nuZ6kVPEk64NY",
  "name": "Deaven Wink",
  "uri": "spotify:artist:2gfEBGQv2nuZ6kVPEk64NY",
  "followers": {
    "href": null,
    "total": 1655
  },
  "genres": [

  ],
  "images": [
    {
      "height": 640,
      "url": "https://i.scdn.co/image/ab6761610000e5eba4bef36cabebb255092fe20b",
      "width": 640
    },
    {
      "height": 320,
      "url": "https://i.scdn.co/image/ab67616100005174a4bef36cabebb255092fe20b",
      "width": 320
    },
    {
      "height": 160,
      "url": "https://i.scdn.co/image/ab6761610000f178a4bef36cabebb255092fe20b",
      "width": 160
    }
  ],
  "popularity": 23,
  "external_urls": {
    "spotify": "https://open.spotify.com/artist/2gfEBGQv2nuZ6kVPEk64NY"
  }
}