{
  "id": "2iDjBG7xQv4hgKTgh6jhs6",
  "name": "skoolio",
  "uri": "spotify:artist:2iDjBG7xQv4hgKTgh6jhs6",
  "followers": {
    "href": null,
    "total": 175
  },
  "genres": [

  ],
  "images": [
    {
      "height": 640,
      "url": "https://i.scdn.co/image/ab6761610000e5eb482d1eb24655dac55cec3187",
      "width": 640
    },
    {
      "height": 320,
      "url": "https://i.scdn.co/image/ab67616100005174482d1eb24655dac55cec3187",
      "width": 320
    },
    {
      "height": 160,
      "url": "https://i.scdn.co/image/ab6761610000f178482d1eb24655dac55cec3187",
      "width": 160
    }
  ],
  "popularity": 5,
  "external_urls": {
    "spotify": "https://open.spotify.com/artist/2iDjBG7xQv4hgKTgh6jhs6"
  }
}