{
  "id": "2MJ05v517Lc02HwPHVSDys",
  "name": "The Eternal Twilight",
  "uri": "spotify:artist:2MJ05v517Lc02HwPHVSDys",
  "followers": {
    "href": null,
    "total": 305
  },
  "genres": [
    "ambient post-rock",
    "drift"
  ],
  "images": [
    {
      "height": 640,
      "url": "https://i.scdn.co/image/ab67616d0000b273bb6d242c3727e953852ec305",
      "width": 640
    },
    {
      "height": 300,
      "url": "https://i.scdn.co/image/ab67616d00001e02bb6d242c3727e953852ec305",
      "width": 300
    },
    {
      "height": 64,
      "url": "https://i.scdn.co/image/ab67616d00004851bb6d242c3727e953852ec305",
      "width": 64
    }
  ],
  "popularity": 3,
  "external_urls": {
    "spotify": "https://open.spotify.com/artist/2MJ05v517Lc02HwPHVSDys"
  }
}