{
  "id": "2Qi2XnWCXvyaIxxj3PbYTi",
  "name": "Liers In Wait",
  "uri": "spotify:artist:2Qi2XnWCXvyaIxxj3PbYTi",
  "followers": {
    "href": null,
    "total": 2410
  },
  "genres": [
    "gothenburg metal",
    "swedish death metal",
    "swedish metal"
  ],
  "images": [
    {
      "height": 640,
      "url": "https://i.scdn.co/image/ab67616d0000b2731f63333fd3019cbf7bcc3418",
      "width": 640
    },
    {
      "height": 300,
      "url": "https://i.scdn.co/image/ab67616d00001e021f63333fd3019cbf7bcc3418",
      "width": 300
    },
    {
      "height": 64,
      "url": "https://i.scdn.co/image/ab67616d000048511f63333fd3019cbf7bcc3418",
      "width": 64
    }
  ],
  "popularity": 3,
  "external_urls": {
    "spotify": "https://open.spotify.com/artist/2Qi2XnWCXvyaIxxj3PbYTi"
  }
}