{
  "id": "2uMEr7c0zWQrtoAzebTMsa",
  "name": "Charlie Bereal",
  "uri": "spotify:artist:2uMEr7c0zWQrtoAzebTMsa",
  "followers": {
    "href": null,
    "total": 3770
  },
  "genres": [

  ],
  "images": [
    {
      "height": 640,
      "url": "https://i.scdn.co/image/ab6761610000e5ebd4d3fd143baa578d9bfe33e6",
      "width": 640
    },
    {
      "height": 320,
      "url": "https://i.scdn.co/image/ab67616100005174d4d3fd143baa578d9bfe33e6",
      "width": 320
    },
    {
      "height": 160,
      "url": "https://i.scdn.co/image/ab6761610000f178d4d3fd143baa578d9bfe33e6",
      "width": 160
    }
  ],
  "popularity": 31,
  "external_urls": {
    "spotify": "https://open.spotify.com/artist/2uMEr7c0zWQrtoAzebTMsa"
  }
}