{
  "id": "2vKO76QBYwcmlicGUfeVcu",
  "name": "Chase Makai",
  "uri": "spotify:artist:2vKO76QBYwcmlicGUfeVcu",
  "followers": {
    "href": null,
    "total": 394
  },
  "genres": [

  ],
  "images": [
    {
      "height": 640,
      "url": "https://i.scdn.co/image/ab67616d0000b2730cce1fbbbc678c7085b0b3d3",
      "width": 640
    },
    {
      "height": 300,
      "url": "https://i.scdn.co/image/ab67616d00001e020cce1fbbbc678c7085b0b3d3",
      "width": 300
    },
    {
      "height": 64,
      "url": "https://i.scdn.co/image/ab67616d000048510cce1fbbbc678c7085b0b3d3",
      "width": 64
    }
  ],
  "popularity": 0,
  "external_urls": {
    "spotify": "https://open.spotify.com/artist/2vKO76QBYwcmlicGUfeVcu"
  }
}