{
  "id": "39arl4QmjqYbuq7GzoaTLj",
  "name": "Jimmy Johns",
  "uri": "spotify:artist:39arl4QmjqYbuq7GzoaTLj",
  "followers": {
    "href": null,
    "total": 528
  },
  "genres": [

  ],
  "images": [
    {
      "height": 640,
      "url": "https://i.scdn.co/image/ab67616d0000b27300b07334dd5e80cf55d8f784",
      "width": 640
    },
    {
      "height": 300,
      "url": "https://i.scdn.co/image/ab67616d00001e022ace5cf6ae388542eec5195e",
      "width": 300
    },
    {
      "height": 64,
      "url": "https://i.scdn.co/image/ab67616d0000485100b07334dd5e80cf55d8f784",
      "width": 64
    }
  ],
  "popularity": 10,
  "external_urls": {
    "spotify": "https://open.spotify.com/artist/39arl4QmjqYbuq7GzoaTLj"
  }
}