{
  "id": "3hhw6Bz7XB7CxXrKldj5YQ",
  "name": "Casa de Hijos",
  "uri": "spotify:artist:3hhw6Bz7XB7CxXrKldj5YQ",
  "followers": {
    "href": null,
    "total": 2388
  },
  "genres": [

  ],
  "images": [
    {
      "height": 640,
      "url": "https://i.scdn.co/image/ab67616d0000b2734566c8393be7d35f056c358c",
      "width": 640
    },
    {
      "height": 300,
      "url": "https://i.scdn.co/image/ab67616d00001e024566c8393be7d35f056c358c",
      "width": 300
    },
    {
      "height": 64,
      "url": "https://i.scdn.co/image/ab67616d000048514566c8393be7d35f056c358c",
      "width": 64
    }
  ],
  "popularity": 11,
  "external_urls": {
    "spotify": "https://open.spotify.com/artist/3hhw6Bz7XB7CxXrKldj5YQ"
  }
}