{
  "id": "3IWv5Qx22vgGQF7SvoSfje",
  "name": "Tamara Luonto",
  "uri": "spotify:artist:3IWv5Qx22vgGQF7SvoSfje",
  "followers": {
    "href": null,
    "total": 984
  },
  "genres": [
    "finnish indie",
    "finnish punk"
  ],
  "images": [
    {
      "height": 640,
      "url": "https://i.scdn.co/image/ab67616d0000b2732a437ff66faa695182fd340d",
      "width": 640
    },
    {
      "height": 300,
      "url": "https://i.scdn.co/image/ab67616d00001e022a437ff66faa695182fd340d",
      "width": 300
    },
    {
      "height": 64,
      "url": "https://i.scdn.co/image/ab67616d000048512a437ff66faa695182fd340d",
      "width": 64
    }
  ],
  "popularity": 9,
  "external_urls": {
    "spotify": "https://open.spotify.com/artist/3IWv5Qx22vgGQF7SvoSfje"
  }
}