{
  "id": "3NkNKt7L8KOLbBzeViaRko",
  "name": "Amarnu",
  "uri": "spotify:artist:3NkNKt7L8KOLbBzeViaRko",
  "followers": {
    "href": null,
    "total": 99
  },
  "genres": [

  ],
  "images": [
    {
      "height": 640,
      "url": "https://i.scdn.co/image/ab6761610000e5eb98ffdaf88e2b7e88f667a1b0",
      "width": 640
    },
    {
      "height": 320,
      "url": "https://i.scdn.co/image/ab6761610000517498ffdaf88e2b7e88f667a1b0",
      "width": 320
    },
    {
      "height": 160,
      "url": "https://i.scdn.co/image/ab6761610000f17898ffdaf88e2b7e88f667a1b0",
      "width": 160
    }
  ],
  "popularity": 4,
  "external_urls": {
    "spotify": "https://open.spotify.com/artist/3NkNKt7L8KOLbBzeViaRko"
  }
}