{
  "id": "3r94PF71LWRI5K6wqclNjQ",
  "name": "Chapterhouse",
  "uri": "spotify:artist:3r94PF71LWRI5K6wqclNjQ",
  "followers": {
    "href": null,
    "total": 68576
  },
  "genres": [
    "dream pop",
    "dreamgaze",
    "nu gaze",
    "reading indie",
    "shoegaze"
  ],
  "images": [
    {
      "height": 750,
      "url": "https://i.scdn.co/image/e00fcc7f12f99031c4ea6c4970d5116928c9d195",
      "width": 1000
    },
    {
      "height": 480,
      "url": "https://i.scdn.co/image/1bd3cb9bacdf76cd5339a4b78dd69205666118cd",
      "width": 640
    },
    {
      "height": 150,
      "url": "https://i.scdn.co/image/152206e6f78f57ee06d1b772e8c95ecb6c9b0e0c",
      "width": 200
    },
    {
      "height": 48,
      "url": "https://i.scdn.co/image/da932b7df3cc7337997e08779b5d6123829ade26",
      "width": 64
    }
  ],
  "popularity": 35,
  "external_urls": {
    "spotify": "https://open.spotify.com/artist/3r94PF71LWRI5K6wqclNjQ"
  }
}