{
  "id": "46krZvlHGa7xguXwrR65yz",
  "name": "небо над головой",
  "uri": "spotify:artist:46krZvlHGa7xguXwrR65yz",
  "followers": {
    "href": null,
    "total": 10570
  },
  "genres": [
    "russian post-punk"
  ],
  "images": [
    {
      "height": 640,
      "url": "https://i.scdn.co/image/ab67616d0000b273f10c6a10f36a7f1fc3524d16",
      "width": 640
    },
    {
      "height": 300,
      "url": "https://i.scdn.co/image/ab67616d00001e02f10c6a10f36a7f1fc3524d16",
      "width": 300
    },
    {
      "height": 64,
      "url": "https://i.scdn.co/image/ab67616d00004851f10c6a10f36a7f1fc3524d16",
      "width": 64
    }
  ],
  "popularity": 35,
  "external_urls": {
    "spotify": "https://open.spotify.com/artist/46krZvlHGa7xguXwrR65yz"
  }
}