{
  "id": "4ATcUHoVnPzAkHI2X6SxIe",
  "name": "No On 15",
  "uri": "spotify:artist:4ATcUHoVnPzAkHI2X6SxIe",
  "followers": {
    "href": null,
    "total": 102
  },
  "genres": [

  ],
  "images": [
    {
      "height": 640,
      "url": "https://i.scdn.co/image/ab67616d0000b273c68d6d5c696ec4d9dd1e5ec5",
      "width": 640
    },
    {
      "height": 300,
      "url": "https://i.scdn.co/image/ab67616d00001e02c68d6d5c696ec4d9dd1e5ec5",
      "width": 300
    },
    {
      "height": 64,
      "url": "https://i.scdn.co/image/ab67616d00004851c68d6d5c696ec4d9dd1e5ec5",
      "width": 64
    }
  ],
  "popularity": 0,
  "external_urls": {
    "spotify": "https://open.spotify.com/artist/4ATcUHoVnPzAkHI2X6SxIe"
  }
}