{
  "id": "4DKcECb5dOEsS7BwgLqaIJ",
  "name": "Seigo Aoyama",
  "uri": "spotify:artist:4DKcECb5dOEsS7BwgLqaIJ",
  "followers": {
    "href": null,
    "total": 164
  },
  "genres": [
    "organic ambient"
  ],
  "images": [
    {
      "height": 640,
      "url": "https://i.scdn.co/image/ab67616d0000b2736fc9225aa32dde3d88cc1dbc",
      "width": 640
    },
    {
      "height": 300,
      "url": "https://i.scdn.co/image/ab67616d00001e026fc9225aa32dde3d88cc1dbc",
      "width": 300
    },
    {
      "height": 64,
      "url": "https://i.scdn.co/image/ab67616d000048516fc9225aa32dde3d88cc1dbc",
      "width": 64
    }
  ],
  "popularity": 3,
  "external_urls": {
    "spotify": "https://open.spotify.com/artist/4DKcECb5dOEsS7BwgLqaIJ"
  }
}