{
  "id": "4eLokgCnO4doiOAdkscw1a",
  "name": "Helical Boys",
  "uri": "spotify:artist:4eLokgCnO4doiOAdkscw1a",
  "followers": {
    "href": null,
    "total": 301
  },
  "genres": [

  ],
  "images": [
    {
      "height": 640,
      "url": "https://i.scdn.co/image/ab6761610000e5ebb3c6a5a7301ea7a3fcc12637",
      "width": 640
    },
    {
      "height": 320,
      "url": "https://i.scdn.co/image/ab67616100005174b3c6a5a7301ea7a3fcc12637",
      "width": 320
    },
    {
      "height": 160,
      "url": "https://i.scdn.co/image/ab6761610000f178b3c6a5a7301ea7a3fcc12637",
      "width": 160
    }
  ],
  "popularity": 1,
  "external_urls": {
    "spotify": "https://open.spotify.com/artist/4eLokgCnO4doiOAdkscw1a"
  }
}