{
  "id": "4MMEYqTez1VXF05M77ZvvK",
  "name": "Nouveaux",
  "uri": "spotify:artist:4MMEYqTez1VXF05M77ZvvK",
  "followers": {
    "href": null,
    "total": 273
  },
  "genres": [

  ],
  "images": [
    {
      "height": 640,
      "url": "https://i.scdn.co/image/ab67616d0000b273502322e3f1951dd21c34c94e",
      "width": 640
    },
    {
      "height": 300,
      "url": "https://i.scdn.co/image/ab67616d00001e02502322e3f1951dd21c34c94e",
      "width": 300
    },
    {
      "height": 64,
      "url": "https://i.scdn.co/image/ab67616d00004851502322e3f1951dd21c34c94e",
      "width": 64
    }
  ],
  "popularity": 0,
  "external_urls": {
    "spotify": "https://open.spotify.com/artist/4MMEYqTez1VXF05M77ZvvK"
  }
}