{
  "id": "4NlQZi22PXtCPOZ8PfnTJT",
  "name": "Missstand",
  "uri": "spotify:artist:4NlQZi22PXtCPOZ8PfnTJT",
  "followers": {
    "href": null,
    "total": 3482
  },
  "genres": [
    "austrian punk",
    "german punk",
    "german punk rock"
  ],
  "images": [
    {
      "height": 640,
      "url": "https://i.scdn.co/image/ab6761610000e5eb4ab3ed26e6693aec4f4bbb75",
      "width": 640
    },
    {
      "height": 320,
      "url": "https://i.scdn.co/image/ab676161000051744ab3ed26e6693aec4f4bbb75",
      "width": 320
    },
    {
      "height": 160,
      "url": "https://i.scdn.co/image/ab6761610000f1784ab3ed26e6693aec4f4bbb75",
      "width": 160
    }
  ],
  "popularity": 22,
  "external_urls": {
    "spotify": "https://open.spotify.com/artist/4NlQZi22PXtCPOZ8PfnTJT"
  }
}