{
  "id": "4POFwgsibhA3uhQo08kUEw",
  "name": "Greenslade",
  "uri": "spotify:artist:4POFwgsibhA3uhQo08kUEw",
  "followers": {
    "href": null,
    "total": 22835
  },
  "genres": [
    "italian progressive rock",
    "progressive rock",
    "symphonic rock",
    "synth prog"
  ],
  "images": [
    {
      "height": 640,
      "url": "https://i.scdn.co/image/ab67616d0000b273872cbecdedcb4db924f8d535",
      "width": 640
    },
    {
      "height": 300,
      "url": "https://i.scdn.co/image/ab67616d00001e02872cbecdedcb4db924f8d535",
      "width": 300
    },
    {
      "height": 64,
      "url": "https://i.scdn.co/image/ab67616d00004851872cbecdedcb4db924f8d535",
      "width": 64
    }
  ],
  "popularity": 21,
  "external_urls": {
    "spotify": "https://open.spotify.com/artist/4POFwgsibhA3uhQo08kUEw"
  }
}