{
  "id": "4wsgkOQyaMrUeZIZHeXk7S",
  "name": "Guns For Frogs",
  "uri": "spotify:artist:4wsgkOQyaMrUeZIZHeXk7S",
  "followers": {
    "href": null,
    "total": 290
  },
  "genres": [

  ],
  "images": [
    {
      "height": 640,
      "url": "https://i.scdn.co/image/ab6761610000e5ebf4add5d457fb2d0dbffd71fa",
      "width": 640
    },
    {
      "height": 320,
      "url": "https://i.scdn.co/image/ab67616100005174f4add5d457fb2d0dbffd71fa",
      "width": 320
    },
    {
      "height": 160,
      "url": "https://i.scdn.co/image/ab6761610000f178f4add5d457fb2d0dbffd71fa",
      "width": 160
    }
  ],
  "popularity": 7,
  "external_urls": {
    "spotify": "https://open.spotify.com/artist/4wsgkOQyaMrUeZIZHeXk7S"
  }
}