{
  "id": "4yBBRaHrslHgo6ccSuTkgu",
  "name": "N2MU",
  "uri": "spotify:artist:4yBBRaHrslHgo6ccSuTkgu",
  "followers": {
    "href": null,
    "total": 588
  },
  "genres": [

  ],
  "images": [
    {
      "height": 640,
      "url": "https://i.scdn.co/image/ab6761610000e5ebe249c6d90b7e882f86233cf7",
      "width": 640
    },
    {
      "height": 320,
      "url": "https://i.scdn.co/image/ab67616100005174e249c6d90b7e882f86233cf7",
      "width": 320
    },
    {
      "height": 160,
      "url": "https://i.scdn.co/image/ab6761610000f178e249c6d90b7e882f86233cf7",
      "width": 160
    }
  ],
  "popularity": 0,
  "external_urls": {
    "spotify": "https://open.spotify.com/artist/4yBBRaHrslHgo6ccSuTkgu"
  }
}