{
  "id": "55qM8Z3mN4hkUkdqpsm7w8",
  "name": "Azziah",
  "uri": "spotify:artist:55qM8Z3mN4hkUkdqpsm7w8",
  "followers": {
    "href": null,
    "total": 257
  },
  "genres": [

  ],
  "images": [
    {
      "height": 640,
      "url": "https://i.scdn.co/image/ab6761610000e5ebca490cb2e31e7309d925f17d",
      "width": 640
    },
    {
      "height": 320,
      "url": "https://i.scdn.co/image/ab67616100005174ca490cb2e31e7309d925f17d",
      "width": 320
    },
    {
      "height": 160,
      "url": "https://i.scdn.co/image/ab6761610000f178ca490cb2e31e7309d925f17d",
      "width": 160
    }
  ],
  "popularity": 8,
  "external_urls": {
    "spotify": "https://open.spotify.com/artist/55qM8Z3mN4hkUkdqpsm7w8"
  }
}