{"id":"58UIAmrUf6QUx9nG1MflXb","name":"Michael Formanek Very Practical Trio","uri":"spotify:artist:58UIAmrUf6QUx9nG1MflXb","followers":{"href":null,"total":91},"genres":["free jazz","avant-garde","nu jazz"],"images":[{"url":"https://i.scdn.co/image/ab67616d0000b27318183720b0d33ed23e5b9eb0","height":640,"width":640},{"url":"https://i.scdn.co/image/ab67616d00001e0218183720b0d33ed23e5b9eb0","height":300,"width":300},{"url":"https://i.scdn.co/image/ab67616d0000485118183720b0d33ed23e5b9eb0","height":64,"width":64}],"popularity":0,"external_urls":{"spotify":"https://open.spotify.com/artist/58UIAmrUf6QUx9nG1MflXb"}}