{
  "id": "59h090AbCmN56eMMI0CdeU",
  "name": "Akulta",
  "uri": "spotify:artist:59h090AbCmN56eMMI0CdeU",
  "followers": {
    "href": null,
    "total": 104
  },
  "genres": [
    "chillhop"
  ],
  "images": [
    {
      "height": 640,
      "url": "https://i.scdn.co/image/ab6761610000e5eb27e0d4a8a266e3d417b121dd",
      "width": 640
    },
    {
      "height": 320,
      "url": "https://i.scdn.co/image/ab6761610000517427e0d4a8a266e3d417b121dd",
      "width": 320
    },
    {
      "height": 160,
      "url": "https://i.scdn.co/image/ab6761610000f17827e0d4a8a266e3d417b121dd",
      "width": 160
    }
  ],
  "popularity": 11,
  "external_urls": {
    "spotify": "https://open.spotify.com/artist/59h090AbCmN56eMMI0CdeU"
  }
}