{
  "id": "5eZlinrRl0zTwoA1PN0gir",
  "name": "Shunzo Ohno",
  "uri": "spotify:artist:5eZlinrRl0zTwoA1PN0gir",
  "followers": {
    "href": null,
    "total": 1089
  },
  "genres": [
    "classic japanese jazz",
    "japanese jazz"
  ],
  "images": [
    {
      "height": 640,
      "url": "https://i.scdn.co/image/ab6761610000e5ebaaf27f796a907bd26160661b",
      "width": 640
    },
    {
      "height": 320,
      "url": "https://i.scdn.co/image/ab67616100005174aaf27f796a907bd26160661b",
      "width": 320
    },
    {
      "height": 160,
      "url": "https://i.scdn.co/image/ab6761610000f178aaf27f796a907bd26160661b",
      "width": 160
    }
  ],
  "popularity": 12,
  "external_urls": {
    "spotify": "https://open.spotify.com/artist/5eZlinrRl0zTwoA1PN0gir"
  }
}