{
  "id": "5fIZxtu9KYwRi3MnLEVLCC",
  "name": "lapix",
  "uri": "spotify:artist:5fIZxtu9KYwRi3MnLEVLCC",
  "followers": {
    "href": null,
    "total": 26223
  },
  "genres": [
    "j-core"
  ],
  "images": [
    {
      "height": 640,
      "url": "https://i.scdn.co/image/ab67616d0000b2732581386c8c7e9440849cff5e",
      "width": 640
    },
    {
      "height": 300,
      "url": "https://i.scdn.co/image/ab67616d00001e022581386c8c7e9440849cff5e",
      "width": 300
    },
    {
      "height": 64,
      "url": "https://i.scdn.co/image/ab67616d000048512581386c8c7e9440849cff5e",
      "width": 64
    }
  ],
  "popularity": 34,
  "external_urls": {
    "spotify": "https://open.spotify.com/artist/5fIZxtu9KYwRi3MnLEVLCC"
  }
}