{"id":"5If5Tdg66Q5X3L57G7A6Pn","name":"Thylacine","uri":"spotify:artist:5If5Tdg66Q5X3L57G7A6Pn","followers":{"href":null,"total":162136},"genres":["french indie pop","french indietronica","new french touch"],"images":[{"url":"https://i.scdn.co/image/ab6761610000e5eb85d18acb6ce3a8a49dd318aa","height":640,"width":640},{"url":"https://i.scdn.co/image/ab6761610000517485d18acb6ce3a8a49dd318aa","height":320,"width":320},{"url":"https://i.scdn.co/image/ab6761610000f17885d18acb6ce3a8a49dd318aa","height":160,"width":160}],"popularity":50,"external_urls":{"spotify":"https://open.spotify.com/artist/5If5Tdg66Q5X3L57G7A6Pn"}}