{
  "id": "6h8VOeAXc8EgwqQ9YMH1rZ",
  "name": "The Deadlights",
  "uri": "spotify:artist:6h8VOeAXc8EgwqQ9YMH1rZ",
  "followers": {
    "href": null,
    "total": 5325
  },
  "genres": [
    "alternative metalcore"
  ],
  "images": [
    {
      "height": 640,
      "url": "https://i.scdn.co/image/ab67616d0000b2734eca34eee92dab400cce42cd",
      "width": 640
    },
    {
      "height": 300,
      "url": "https://i.scdn.co/image/ab67616d00001e024eca34eee92dab400cce42cd",
      "width": 300
    },
    {
      "height": 64,
      "url": "https://i.scdn.co/image/ab67616d000048514eca34eee92dab400cce42cd",
      "width": 64
    }
  ],
  "popularity": 11,
  "external_urls": {
    "spotify": "https://open.spotify.com/artist/6h8VOeAXc8EgwqQ9YMH1rZ"
  }
}