{"id":"6HYQuEv4fe2Ln5ClqLq6yw","name":"The Antarcticans","uri":"spotify:artist:6HYQuEv4fe2Ln5ClqLq6yw","followers":{"href":null,"total":155},"genres":["post-rock","math rock","southern hip hop","uk garage"],"images":[{"url":"https://i.scdn.co/image/ab67616d0000b273fff854e78eecd7c2b0dea45b","height":640,"width":640},{"url":"https://i.scdn.co/image/ab67616d00001e02fff854e78eecd7c2b0dea45b","height":300,"width":300},{"url":"https://i.scdn.co/image/ab67616d00004851fff854e78eecd7c2b0dea45b","height":64,"width":64}],"popularity":0,"external_urls":{"spotify":"https://open.spotify.com/artist/6HYQuEv4fe2Ln5ClqLq6yw"}}