{"id":"6ISdh8nhJQIZ141GLZsSrf","name":"Suffering Hour","uri":"spotify:artist:6ISdh8nhJQIZ141GLZsSrf","followers":{"href":null,"total":13823},"genres":["cavernous death metal","dissonant death metal","minneapolis metal","new wave of osdm","voidgaze"],"images":[{"url":"https://i.scdn.co/image/ab6761610000e5eb358d16166f08b60285113106","height":640,"width":640},{"url":"https://i.scdn.co/image/ab67616100005174358d16166f08b60285113106","height":320,"width":320},{"url":"https://i.scdn.co/image/ab6761610000f178358d16166f08b60285113106","height":160,"width":160}],"popularity":14,"external_urls":{"spotify":"https://open.spotify.com/artist/6ISdh8nhJQIZ141GLZsSrf"}}