{
  "id": "6niGWiS0s71bLkfiujlGLf",
  "name": "Mcintosh Noize",
  "uri": "spotify:artist:6niGWiS0s71bLkfiujlGLf",
  "followers": {
    "href": null,
    "total": 43
  },
  "genres": [

  ],
  "images": [
    {
      "height": 640,
      "url": "https://i.scdn.co/image/ab6761610000e5eb70e155110e0b164637924a4b",
      "width": 640
    },
    {
      "height": 320,
      "url": "https://i.scdn.co/image/ab6761610000517470e155110e0b164637924a4b",
      "width": 320
    },
    {
      "height": 160,
      "url": "https://i.scdn.co/image/ab6761610000f17870e155110e0b164637924a4b",
      "width": 160
    }
  ],
  "popularity": 0,
  "external_urls": {
    "spotify": "https://open.spotify.com/artist/6niGWiS0s71bLkfiujlGLf"
  }
}