{
  "id": "6r5QU8r9wS9irHmeehFCNy",
  "name": "DJ Yogurt",
  "uri": "spotify:artist:6r5QU8r9wS9irHmeehFCNy",
  "followers": {
    "href": null,
    "total": 644
  },
  "genres": [

  ],
  "images": [
    {
      "height": 640,
      "url": "https://i.scdn.co/image/ab67616d0000b2730e3b0a3efc7725dedc5b42be",
      "width": 640
    },
    {
      "height": 300,
      "url": "https://i.scdn.co/image/ab67616d00001e020e3b0a3efc7725dedc5b42be",
      "width": 300
    },
    {
      "height": 64,
      "url": "https://i.scdn.co/image/ab67616d000048510e3b0a3efc7725dedc5b42be",
      "width": 64
    }
  ],
  "popularity": 6,
  "external_urls": {
    "spotify": "https://open.spotify.com/artist/6r5QU8r9wS9irHmeehFCNy"
  }
}