{"id":"6r90tCIVqGvSHLouiTUhQW","name":"Los Rancheros De Rio Maule","uri":"spotify:artist:6r90tCIVqGvSHLouiTUhQW","followers":{"href":null,"total":133603},"genres":["cumbia chilena","cumbia ranchera"],"images":[{"url":"https://i.scdn.co/image/ab6761610000e5ebf10e077394102543a19f6a01","height":640,"width":640},{"url":"https://i.scdn.co/image/ab67616100005174f10e077394102543a19f6a01","height":320,"width":320},{"url":"https://i.scdn.co/image/ab6761610000f178f10e077394102543a19f6a01","height":160,"width":160}],"popularity":51,"external_urls":{"spotify":"https://open.spotify.com/artist/6r90tCIVqGvSHLouiTUhQW"}}