{
  "id": "6UxdwOqc96xNJhl45OEG8C",
  "name": "Disfare",
  "uri": "spotify:artist:6UxdwOqc96xNJhl45OEG8C",
  "followers": {
    "href": null,
    "total": 1608
  },
  "genres": [
    "indonesian hardcore"
  ],
  "images": [
    {
      "height": 640,
      "url": "https://i.scdn.co/image/ab67616d0000b273a1f9ea4f34a2319f0bb89c4b",
      "width": 640
    },
    {
      "height": 300,
      "url": "https://i.scdn.co/image/ab67616d00001e02a1f9ea4f34a2319f0bb89c4b",
      "width": 300
    },
    {
      "height": 64,
      "url": "https://i.scdn.co/image/ab67616d00004851a1f9ea4f34a2319f0bb89c4b",
      "width": 64
    }
  ],
  "popularity": 1,
  "external_urls": {
    "spotify": "https://open.spotify.com/artist/6UxdwOqc96xNJhl45OEG8C"
  }
}