{"id":"6whFEcaV75AmQMiwlfaxvc","name":"QUEEN BEE","uri":"spotify:artist:6whFEcaV75AmQMiwlfaxvc","followers":{"href":null,"total":427233},"genres":["anime rock","dance rock","j-pop","j-rock"],"images":[{"url":"https://i.scdn.co/image/ab6761610000e5ebda488f9ddaea253b510b367d","height":640,"width":640},{"url":"https://i.scdn.co/image/ab67616100005174da488f9ddaea253b510b367d","height":320,"width":320},{"url":"https://i.scdn.co/image/ab6761610000f178da488f9ddaea253b510b367d","height":160,"width":160}],"popularity":57,"external_urls":{"spotify":"https://open.spotify.com/artist/6whFEcaV75AmQMiwlfaxvc"}}