{
  "id": "75Q3EDCS37rtHGINoCsfQs",
  "name": "Top Floor Boss",
  "uri": "spotify:artist:75Q3EDCS37rtHGINoCsfQs",
  "followers": {
    "href": null,
    "total": 1563
  },
  "genres": [

  ],
  "images": [
    {
      "height": 640,
      "url": "https://i.scdn.co/image/ab6761610000e5eb64ec565f11b96f0abe074fd3",
      "width": 640
    },
    {
      "height": 320,
      "url": "https://i.scdn.co/image/ab6761610000517464ec565f11b96f0abe074fd3",
      "width": 320
    },
    {
      "height": 160,
      "url": "https://i.scdn.co/image/ab6761610000f17864ec565f11b96f0abe074fd3",
      "width": 160
    }
  ],
  "popularity": 36,
  "external_urls": {
    "spotify": "https://open.spotify.com/artist/75Q3EDCS37rtHGINoCsfQs"
  }
}