{
  "id": "78ha7M7CTuRTt4QQ7uVhVn",
  "name": "kian",
  "uri": "spotify:artist:78ha7M7CTuRTt4QQ7uVhVn",
  "followers": {
    "href": null,
    "total": 926
  },
  "genres": [

  ],
  "images": [
    {
      "height": 640,
      "url": "https://i.scdn.co/image/ab6761610000e5ebb2b645a5832b7423c0b7ca9f",
      "width": 640
    },
    {
      "height": 320,
      "url": "https://i.scdn.co/image/ab67616100005174b2b645a5832b7423c0b7ca9f",
      "width": 320
    },
    {
      "height": 160,
      "url": "https://i.scdn.co/image/ab6761610000f178b2b645a5832b7423c0b7ca9f",
      "width": 160
    }
  ],
  "popularity": 7,
  "external_urls": {
    "spotify": "https://open.spotify.com/artist/78ha7M7CTuRTt4QQ7uVhVn"
  }
}