{
  "id": "7bHvrn7cZ1d8b7Wa3jgbVo",
  "name": "Mortus Stella",
  "uri": "spotify:artist:7bHvrn7cZ1d8b7Wa3jgbVo",
  "followers": {
    "href": null,
    "total": 289
  },
  "genres": [

  ],
  "images": [
    {
      "height": 640,
      "url": "https://i.scdn.co/image/ab6761610000e5ebae3d9adc4749aaddd076dc74",
      "width": 640
    },
    {
      "height": 320,
      "url": "https://i.scdn.co/image/ab67616100005174ae3d9adc4749aaddd076dc74",
      "width": 320
    },
    {
      "height": 160,
      "url": "https://i.scdn.co/image/ab6761610000f178ae3d9adc4749aaddd076dc74",
      "width": 160
    }
  ],
  "popularity": 1,
  "external_urls": {
    "spotify": "https://open.spotify.com/artist/7bHvrn7cZ1d8b7Wa3jgbVo"
  }
}