{
  "id": "7bV1kbQdUraAIL5ugmCP7i",
  "name": "María Delitos",
  "uri": "spotify:artist:7bV1kbQdUraAIL5ugmCP7i",
  "followers": {
    "href": null,
    "total": 143
  },
  "genres": [

  ],
  "images": [
    {
      "height": 640,
      "url": "https://i.scdn.co/image/ab6761610000e5ebbba6e22cad7ac62773d38fc3",
      "width": 640
    },
    {
      "height": 320,
      "url": "https://i.scdn.co/image/ab67616100005174bba6e22cad7ac62773d38fc3",
      "width": 320
    },
    {
      "height": 160,
      "url": "https://i.scdn.co/image/ab6761610000f178bba6e22cad7ac62773d38fc3",
      "width": 160
    }
  ],
  "popularity": 1,
  "external_urls": {
    "spotify": "https://open.spotify.com/artist/7bV1kbQdUraAIL5ugmCP7i"
  }
}