{"id":"7d4PEfFPHE4XkZMy2dNjn6","name":"Julian Nates","uri":"spotify:artist:7d4PEfFPHE4XkZMy2dNjn6","followers":{"href":null,"total":3806},"genres":["progressive house","organic house","melodic house","melodic techno"],"images":[{"url":"https://i.scdn.co/image/ab6761610000e5ebd9ea93bc9e07c40d7f8d57d1","height":640,"width":640},{"url":"https://i.scdn.co/image/ab67616100005174d9ea93bc9e07c40d7f8d57d1","height":320,"width":320},{"url":"https://i.scdn.co/image/ab6761610000f178d9ea93bc9e07c40d7f8d57d1","height":160,"width":160}],"popularity":20,"external_urls":{"spotify":"https://open.spotify.com/artist/7d4PEfFPHE4XkZMy2dNjn6"}}