{
  "id": "7Gfv3zz0llLUQ1HhyHSYTl",
  "name": "Yavin",
  "uri": "spotify:artist:7Gfv3zz0llLUQ1HhyHSYTl",
  "followers": {
    "href": null,
    "total": 1207
  },
  "genres": [

  ],
  "images": [
    {
      "height": 640,
      "url": "https://i.scdn.co/image/ab6761610000e5eb771762bbf0f55ed7dabf91d0",
      "width": 640
    },
    {
      "height": 320,
      "url": "https://i.scdn.co/image/ab67616100005174771762bbf0f55ed7dabf91d0",
      "width": 320
    },
    {
      "height": 160,
      "url": "https://i.scdn.co/image/ab6761610000f178771762bbf0f55ed7dabf91d0",
      "width": 160
    }
  ],
  "popularity": 6,
  "external_urls": {
    "spotify": "https://open.spotify.com/artist/7Gfv3zz0llLUQ1HhyHSYTl"
  }
}