{
  "id": "7ik0i1FStirawZVcI4Ehsp",
  "name": "Found Space",
  "uri": "spotify:artist:7ik0i1FStirawZVcI4Ehsp",
  "followers": {
    "href": null,
    "total": 1098
  },
  "genres": [
    "cascadia shoegaze",
    "chill dream pop"
  ],
  "images": [
    {
      "height": 640,
      "url": "https://i.scdn.co/image/ab6761610000e5ebe2c9a1a06701d185948a26c8",
      "width": 640
    },
    {
      "height": 320,
      "url": "https://i.scdn.co/image/ab67616100005174e2c9a1a06701d185948a26c8",
      "width": 320
    },
    {
      "height": 160,
      "url": "https://i.scdn.co/image/ab6761610000f178e2c9a1a06701d185948a26c8",
      "width": 160
    }
  ],
  "popularity": 14,
  "external_urls": {
    "spotify": "https://open.spotify.com/artist/7ik0i1FStirawZVcI4Ehsp"
  }
}