{
  "id": "7IZrghQhI8yXGSjB2SWr0p",
  "name": "soulkids",
  "uri": "spotify:artist:7IZrghQhI8yXGSjB2SWr0p",
  "followers": {
    "href": null,
    "total": 439
  },
  "genres": [

  ],
  "images": [
    {
      "height": 640,
      "url": "https://i.scdn.co/image/ab67616d0000b273544709178890169e3e1bc0df",
      "width": 640
    },
    {
      "height": 300,
      "url": "https://i.scdn.co/image/ab67616d00001e02544709178890169e3e1bc0df",
      "width": 300
    },
    {
      "height": 64,
      "url": "https://i.scdn.co/image/ab67616d00004851544709178890169e3e1bc0df",
      "width": 64
    }
  ],
  "popularity": 2,
  "external_urls": {
    "spotify": "https://open.spotify.com/artist/7IZrghQhI8yXGSjB2SWr0p"
  }
}