{"id":"7jGn8qhLb48n7yMMNfAoHv","name":"Awesome City Club","uri":"spotify:artist:7jGn8qhLb48n7yMMNfAoHv","followers":{"href":null,"total":270710},"genres":["city pop","j-pop","j-rock","japanese alternative rock"],"images":[{"url":"https://i.scdn.co/image/ab6761610000e5ebe6e51b30e6f705cd06d3895f","height":640,"width":640},{"url":"https://i.scdn.co/image/ab67616100005174e6e51b30e6f705cd06d3895f","height":320,"width":320},{"url":"https://i.scdn.co/image/ab6761610000f178e6e51b30e6f705cd06d3895f","height":160,"width":160}],"popularity":48,"external_urls":{"spotify":"https://open.spotify.com/artist/7jGn8qhLb48n7yMMNfAoHv"}}