{
  "id": "7ouOqsXE48Mh2AP9X8Ixxk",
  "name": "Antpile",
  "uri": "spotify:artist:7ouOqsXE48Mh2AP9X8Ixxk",
  "followers": {
    "href": null,
    "total": 43
  },
  "genres": [
    "atlanta punk"
  ],
  "images": [
    {
      "height": 640,
      "url": "https://i.scdn.co/image/ab67616d0000b27355e184e95f8801c81124c08e",
      "width": 640
    },
    {
      "height": 300,
      "url": "https://i.scdn.co/image/ab67616d00001e0255e184e95f8801c81124c08e",
      "width": 300
    },
    {
      "height": 64,
      "url": "https://i.scdn.co/image/ab67616d0000485102913e376fb47a1fbe42eb64",
      "width": 64
    }
  ],
  "popularity": 0,
  "external_urls": {
    "spotify": "https://open.spotify.com/artist/7ouOqsXE48Mh2AP9X8Ixxk"
  }
}