{
  "id": "7p1KdHKrIDsXbiHnRNPOTG",
  "name": "Innanet James",
  "uri": "spotify:artist:7p1KdHKrIDsXbiHnRNPOTG",
  "followers": {
    "href": null,
    "total": 31182
  },
  "genres": [
    "dmv rap"
  ],
  "images": [
    {
      "height": 640,
      "url": "https://i.scdn.co/image/ab6761610000e5eba78ecfd5edc855cb47b590e4",
      "width": 640
    },
    {
      "height": 320,
      "url": "https://i.scdn.co/image/ab67616100005174a78ecfd5edc855cb47b590e4",
      "width": 320
    },
    {
      "height": 160,
      "url": "https://i.scdn.co/image/ab6761610000f178a78ecfd5edc855cb47b590e4",
      "width": 160
    }
  ],
  "popularity": 23,
  "external_urls": {
    "spotify": "https://open.spotify.com/artist/7p1KdHKrIDsXbiHnRNPOTG"
  }
}