{
  "id": "7pgJQJcLMQzelaMlJjXo9u",
  "name": "Static Waves",
  "uri": "spotify:artist:7pgJQJcLMQzelaMlJjXo9u",
  "followers": {
    "href": null,
    "total": 756
  },
  "genres": [
    "indie rockism"
  ],
  "images": [
    {
      "height": 640,
      "url": "https://i.scdn.co/image/ab67616d0000b2736d51d395c753c1bb6853bc5d",
      "width": 640
    },
    {
      "height": 300,
      "url": "https://i.scdn.co/image/ab67616d00001e026d51d395c753c1bb6853bc5d",
      "width": 300
    },
    {
      "height": 64,
      "url": "https://i.scdn.co/image/ab67616d000048516d51d395c753c1bb6853bc5d",
      "width": 64
    }
  ],
  "popularity": 3,
  "external_urls": {
    "spotify": "https://open.spotify.com/artist/7pgJQJcLMQzelaMlJjXo9u"
  }
}