{
  "id": "7tVkoeijZhmwmvtlRrxAT0",
  "name": "Stockz",
  "uri": "spotify:artist:7tVkoeijZhmwmvtlRrxAT0",
  "followers": {
    "href": null,
    "total": 5758
  },
  "genres": [
    "indie hip hop"
  ],
  "images": [
    {
      "height": 640,
      "url": "https://i.scdn.co/image/ab6761610000e5ebd5734c00926b5b65d4a5afb3",
      "width": 640
    },
    {
      "height": 320,
      "url": "https://i.scdn.co/image/ab67616100005174d5734c00926b5b65d4a5afb3",
      "width": 320
    },
    {
      "height": 160,
      "url": "https://i.scdn.co/image/ab6761610000f178d5734c00926b5b65d4a5afb3",
      "width": 160
    }
  ],
  "popularity": 25,
  "external_urls": {
    "spotify": "https://open.spotify.com/artist/7tVkoeijZhmwmvtlRrxAT0"
  }
}